pyjre/__init__.py
pyjre/explorer.py
pyjre-0.0.3.dist-info/METADATA
pyjre-0.0.3.dist-info/WHEEL
pyjre-0.0.3.dist-info/top_level.txt
pyjre-0.0.3.dist-info/RECORD
