Metadata-Version: 2.1
Name: pyjre
Version: 0.0.3
Summary: Wrapper for the Joe Rogan Experience podcase website data.
Home-page: https://github.com/arnavkohli/pyjre
Author: UNKNOWN
Author-email: UNKNOWN
License: UNKNOWN
Platform: UNKNOWN
